{
  "id": "346",
  "name": "Mitchell Jacobson",
  "childhood": {
    "birthPlace": "Atlanta, Georgia, USA",
    "birthPlaceKo": "미국 조지아 애틀란타",
    "familyBackground": "From American family with service industry and hospitality background.",
    "familyBackgroundKo": "부모가 작은 호텔을 소유했던 서비스 산업 및 호스피탈리티 배경이 있는 미국 가족에서.",
    "education": "Georgia Tech, Business Administration and Hospitality Management",
    "educationKo": "조지아 공대, 경영학 및 호스피탈리티 경영",
    "earlyLife": "Worked in family hospitality business before expanding into larger service operations.",
    "earlyLifeKo": "더 큰 서비스 운영으로 확장하기 전 가족 호스피탈리티 사업에서 근무.",
    "source": null
  },
  "careerTimeline": [
    {
      "year": 1995,
      "event": "Took over family hotel and expanded into service business",
      "eventKo": "가족 호텔을 인수하고 서비스 사업으로 확장"
    }
  ],
  "failures": [
    {
      "year": 2008,
      "description": "Hospitality sector downturn during global financial crisis",
      "descriptionKo": "글로벌 금융 위기 중 호스피탈리티 부문 침체",
      "lesson": "Managing operations during cyclical downturns requires careful planning",
      "lessonKo": "주기적 침체 중 운영 관리는 신중한 계획 필요",
      "source": null
    }
  ],
  "wealthHistory": [
    {
      "year": 2018,
      "netWorth": 1.1
    },
    {
      "year": 2020,
      "netWorth": 1.4
    },
    {
      "year": 2023,
      "netWorth": 1.7
    }
  ],
  "quotes": [],
  "books": {
    "authored": [],
    "recommended": []
  },
  "personalTraits": {
    "knownFor": "Building major service industry business in United States",
    "knownForKo": "미국의 주요 서비스 산업 사업 구축",
    "philanthropy": "Worker development and hospitality training programs",
    "philanthropyKo": "노동자 개발 및 호스피탈리티 훈련 프로그램",
    "controversies": null,
    "controversiesKo": null
  },
  "sajuConnection": null
}