{
  "id": "1000", "name": "Patrizio Bertelli", "nameKo": "파트리치오 베르텔리",
  "netWorth": 4.1, "nationality": "IT", "industry": "Fashion & Retail",
  "childhood": { "birthPlace": "Arezzo, Italy", "birthPlaceKo": "이탈리아 아레초",
    "familyBackground": "Born to Italian family.", "familyBackgroundKo": "이탈리아 가정에서 출생.",
    "education": "Italian higher education.", "educationKo": "이탈리아 고등교육.",
    "earlyLife": "Married Miuccia Prada in 1987; became Prada Group co-CEO; transformed Prada into global luxury empire.",
    "earlyLifeKo": "1987 미우치아 프라다와 결혼; Prada Group 공동 CEO가 됨; Prada를 글로벌 럭셔리 제국으로 변환.",
    "source": "https://en.wikipedia.org/wiki/Patrizio_Bertelli" },
  "capitalOrigin": { "typeKo": "mixed", "explanationKo": "Prada 가족 결혼 + 본인 38년 운영." },
  "careerTimeline": [
    { "year": 1977, "age": 31, "event": "Began Italian leather business.", "eventKo": "이탈리아 가죽 사업 시작.", "whyItMatteredKo": "출발선." },
    { "year": 1987, "age": 41, "event": "Married Miuccia Prada; joined Prada Group as CEO.", "eventKo": "미우치아 프라다와 결혼; Prada Group CEO 합류.", "whyItMatteredKo": "Prada 단계." },
    { "year": 1992, "age": 46, "event": "Launched Miu Miu brand with Miuccia.", "eventKo": "미우치아와 Miu Miu 브랜드 출시.", "whyItMatteredKo": "Miu Miu 단계." },
    { "year": 2011, "age": 65, "event": "Prada IPO on Hong Kong Stock Exchange.", "eventKo": "Prada 홍콩 증시 IPO.", "whyItMatteredKo": "공개 시장 단계." },
    { "year": 2025, "age": 79, "event": "Personal net worth at $4.1B per Forbes Real-Time. Continues as Prada Group co-CEO.", "eventKo": "포브스 실시간 기준 개인 순자산 41억 달러. Prada Group 공동 CEO 계속.", "whyItMatteredKo": "Prada 자본 정점." }],
  "turningPoints": [{ "year": 1987, "age": 41, "decisionKo": "미우치아 프라다와 결혼 → Prada CEO", "alternativeKo": "독립 가죽 사업", "outcomeKo": "38년 후 글로벌 럭셔리 메이저 공동 CEO" }],
  "moneyMechanics": { "primaryRevenueKo": "Prada Group(홍콩 증시) 가족 지분", "industryKo": "럭셔리 패션", "businessModelKo": "Prada + Miu Miu + Church's + 럭셔리 매장", "moatKo": "38년 부부 공동 경영 + 럭셔리 브랜드", "luckVsSkillKo": "운(40%): 가족 자본 + 결혼. 실력(60%): 38년 운영." },
  "personalTraits": { "knownFor": "Co-CEO of Prada Group; husband of Miuccia Prada; sailing enthusiast (Luna Rossa Challenge).",
    "knownForKo": "Prada Group 공동 CEO; 미우치아 프라다의 남편; 항해 애호가(Luna Rossa Challenge).",
    "philanthropy": "Fondazione Prada with Miuccia.", "philanthropyKo": "미우치아와 Fondazione Prada.",
    "controversies": "Prada cultural-appropriation controversies; Luna Rossa America's Cup spending criticism.", "controversiesKo": "Prada 문화 차용 논란; Luna Rossa 아메리카스 컵 지출 비판." },
  "characterKo": { "summaryKo": "Prada 38년 공동 CEO + 항해 애호가.", "tagsKo": ["Prada", "Miu Miu", "Luna Rossa"] },
  "failures": [
    { "year": 2020, "description": "COVID-19 closed Prada luxury retail globally.", "descriptionKo": "COVID-19이 Prada 럭셔리 소매를 글로벌 폐쇄.", "lesson": "Luxury retail pandemic-exposed.", "lessonKo": "럭셔리 소매 팬데믹 노출." },
    { "year": 2018, "description": "Prada Pradamalia anti-Semitism controversy.", "descriptionKo": "Prada Pradamalia 반유대주의 논란.", "lesson": "Luxury cultural-sensitivity tail.", "lessonKo": "럭셔리 문화 민감성 잔여." }],
  "wealthHistory": [{ "year": 2015, "netWorth": 7.7 }, { "year": 2020, "netWorth": 1.9 }, { "year": 2024, "netWorth": 3.9 }, { "year": 2025, "netWorth": 4.1 }],
  "wealthHistorySource": "Forbes Real-Time Billionaires archive",
  "quotes": [{ "text": "Luxury is craft turned into desire.", "textKo": "럭셔리는 욕망으로 변환된 장인 기술이다.", "context": "On Prada Group", "contextKo": "Prada Group에 대해", "source": "https://www.prada.com" }],
  "books": { "authored": [], "recommended": [] },
  "sajuConnection": { "summary": "Gyeong-Sul day pillar in Jin month — 'siksin-gyeok', creative output, fitting luxury-fashion co-CEO.", "summaryKo": "경술 일주 + 진월 식신격(창의적 결과물·표현)은 38년 부부 공동 럭셔리 브랜드 운영의 끊임없는 창의적 결과물과 호응합니다. 경금 일간 + 술토 일지·진토 월지의 토 기운이 가족·회사 자본의 안정 기반을 이중으로 강조합니다." }
}
