{
  "id": "3463",
  "name": "Chang Young-shin",
  "nameKo": "장영신",
  "birthday": "1936-05-05",
  "birthPlace": "South Korea",
  "birthPlaceKo": "대한민국",
  "netWorth": "$0.3B",
  "nationality": "KR",
  "industry": "Conglomerate",
  "gender": "F",
  "ilju": "정해",
  "gyeokguk": "정관격",
  "_notes": "billionaires.json 1936-05-05 vs 한국 위키 1936-07-22 — 약 2.5개월 차이. 사주 일관성을 위해 1936-05-05 사용.",
  "childhood": {
    "summaryKo": "1936년 일제 강점기 한반도에서 태어났습니다. 1959년 23세에 애경그룹 창업주 채몽인과 결혼해 평범한 가정주부로 출발했습니다. 1970년 결혼 11년 만에 남편 채몽인이 심장마비로 갑작스럽게 별세하면서 34세에 비누 회사 한 곳을 책임지게 됐습니다. 한국 1세대 여성 기업가로서 본인 학력보다 가문 운명이 인생을 결정한 케이스.",
    "capitalTypeKo": "혼합형 — 남편 사후 가업 인수가 출발점이지만, 본인이 50년 이상 직접 경영해 비누 1개 회사를 41개 계열사 6조원 그룹으로 확장",
    "sources": [
      "https://ko.wikipedia.org/wiki/%EC%9E%A5%EC%98%81%EC%8B%A0",
      "https://www.fntimes.com/html/view.php?ud=202408252254069798dd55077bc2_18",
      "https://namu.wiki/w/%EC%9E%A5%EC%98%81%EC%8B%A0"
    ]
  },
  "capitalOrigin": {
    "type": "mixed",
    "typeKo": "mixed",
    "descriptionKo": "1970년 남편 채몽인 별세로 애경유지공업(비누 회사 1곳)을 인수한 출발점. 이후 본인이 1972년 대표이사 취임, 1985년 그룹 회장에 올라 50년 넘게 직접 운영. 비누 단일 사업을 생활화학(트리오·2080·케라시스), 화장품(에이지투웨니스·루나), 부동산·유통(애경백화점·AK플라자), 항공(제주항공, 2005 합작 설립)으로 확장. 2024년 기준 41개 계열사·6조원 그룹. 한국 최초 여성 CEO이자 1997년 한국여성경제인협회 초대 회장. 본인+가문 합산 AK홀딩스(KOSPI 006840) 지분 약 45%, 본인 직접 보유분은 상대적으로 작음 — 그래서 Forbes 기준 자산은 $0.3B 수준이지만 그룹 영향력은 그보다 훨씬 큽니다. Forbes self-made score 5/10 — 인수가 출발점이지만 본인 50년 운영이 그룹 형태를 만든 경우.",
    "selfMadeScore": 5,
    "sources": [
      "https://www.businesspost.co.kr/BP?command=print&idxno=36492",
      "https://www.fntimes.com/html/view.php?ud=202408252254069798dd55077bc2_18",
      "https://namu.wiki/w/%EC%9E%A5%EC%98%81%EC%8B%A0"
    ]
  },
  "careerTimeline": [
    {
      "year": 1959,
      "age": 23,
      "event": "Married Aekyung Group founder Chae Mong-in",
      "eventKo": "애경그룹 창업주 채몽인과 결혼",
      "whyItMatteredKo": "본인 인생을 가업과 묶은 결혼.",
      "source": "https://ko.wikipedia.org/wiki/%EC%9E%A5%EC%98%81%EC%8B%A0"
    },
    {
      "year": 1970,
      "age": 34,
      "event": "Husband Chae Mong-in died suddenly of a heart attack",
      "eventKo": "남편 채몽인 심장마비로 갑작스러운 별세",
      "whyItMatteredKo": "11년 결혼 끝에 평범한 가정주부에서 비누 회사 단독 책임자로 운명 전환. 그녀의 본격 인생은 여기서 시작.",
      "source": "https://www.businesspost.co.kr/BP?command=print&idxno=36492"
    },
    {
      "year": 1972,
      "age": 36,
      "event": "Appointed CEO of Aekyung Yuji Industries (soap company)",
      "eventKo": "애경유지공업 대표이사 취임",
      "whyItMatteredKo": "한국 최초 여성 CEO. 비누 회사를 본격 운영 시작.",
      "source": "https://www.fntimes.com/html/view.php?ud=202408252254069798dd55077bc2_18"
    },
    {
      "year": 1985,
      "age": 49,
      "event": "Appointed Chairman of Aekyung Group",
      "eventKo": "애경그룹 회장 취임",
      "whyItMatteredKo": "비누 1개 회사에서 그룹 형태로 확장.",
      "source": "https://ko.wikipedia.org/wiki/%EC%9E%A5%EC%98%81%EC%8B%A0"
    },
    {
      "year": 1997,
      "age": 61,
      "event": "First Chair of the Korea Federation of Women Entrepreneurs",
      "eventKo": "한국여성경제인협회 초대 회장",
      "whyItMatteredKo": "한국 여성 기업가 1세대의 공식 정체성.",
      "source": "https://www.fntimes.com/html/view.php?ud=202408252254069798dd55077bc2_18"
    },
    {
      "year": 1999,
      "age": 63,
      "event": "Vice Chairman of the Federation of Korean Industries (FKI)",
      "eventKo": "전국경제인연합회 부회장",
      "whyItMatteredKo": "한국 재계 핵심 협의체 진입한 첫 여성.",
      "source": "https://www.fntimes.com/html/view.php?ud=202408252254069798dd55077bc2_18"
    },
    {
      "year": 2005,
      "age": 69,
      "event": "Co-founded Jeju Air via JV with Jeju Special Self-Governing Province",
      "eventKo": "제주특별자치도와 합작해 제주항공 설립",
      "whyItMatteredKo": "비누·화장품 그룹의 항공 산업 진출. AK홀딩스 50.37% 지배의 한국 1위 LCC로 성장.",
      "source": "https://namu.wiki/w/%EC%9E%A5%EC%98%81%EC%8B%A0"
    },
    {
      "year": 2013,
      "age": 77,
      "event": "AK Holdings established as group holding company; long-son Chae Hyung-suk leads day-to-day",
      "eventKo": "AK홀딩스 출범 — 장남 채형석 부회장이 일선 운영",
      "whyItMatteredKo": "지주회사 체제 전환 + 2세 본격 등판.",
      "source": "https://www.businesspost.co.kr/BP?command=article_view&num=279334"
    },
    {
      "year": 2018,
      "age": 82,
      "event": "Aekyung Industrial cosmetics brands AGE 20's and Luna become export hits to China",
      "eventKo": "애경산업 화장품 에이지투웨니스·루나 중국 수출 폭발",
      "whyItMatteredKo": "비누·치약 회사가 K-뷰티 중국 수출주로 변신.",
      "source": "https://www.fntimes.com/html/view.php?ud=202408252254069798dd55077bc2_18"
    },
    {
      "year": 2024,
      "age": 88,
      "event": "Jeju Air Flight 2216 disaster at Muan: 179 of 181 dead. Chang issued public apology as group chair",
      "eventKo": "제주항공 무안 참사 — 181명 중 179명 사망. 88세에 그룹 회장으로 대국민 공식 사과",
      "whyItMatteredKo": "그룹 사상 최대 위기. 1970년 남편 별세 이래 본인 인생의 두 번째 분기점.",
      "source": "https://www.bizhankook.com/bk/article/28863"
    }
  ],
  "turningPoints": [
    {
      "year": 1970,
      "ageAtTime": 34,
      "decisionKo": "남편 별세 후 가업을 처분하지 않고 본인이 직접 인수해 경영",
      "alternativeKo": "회사를 매각하고 평범한 미망인으로 살았다면 한국 최초 여성 CEO도 애경그룹도 없었을 것.",
      "outcomeKo": "비누 회사 1곳 → 41개 계열사·6조원 그룹. 한국 1세대 여성 기업가의 표준 모델."
    },
    {
      "year": 2005,
      "ageAtTime": 69,
      "decisionKo": "비누·화장품 회사가 제주특별자치도와 합작해 항공사 설립",
      "alternativeKo": "기존 생활화학·유통에 집중했다면 항공 사고 리스크 자체가 없었을 것.",
      "outcomeKo": "한국 1위 LCC로 성장 + 19년 후 그룹 사상 최대 비극의 진앙."
    },
    {
      "year": 2024,
      "ageAtTime": 88,
      "decisionKo": "은둔 모드를 깨고 88세에 직접 대국민 공식 사과",
      "alternativeKo": "장남 채형석 부회장에게 사과를 일임했다면 오너 책임 회피 비판이 더 컸을 것.",
      "outcomeKo": "그룹 위기 한가운데 직접 책임지는 모습 — 평가는 진행형."
    }
  ],
  "moneyMechanics": {
    "primaryIncomeSourceKo": "AK홀딩스(KOSPI 006840) + 애경산업 + 제주항공 등 가문 합산 지분 약 45%. 본인 직접 보유분은 상대적으로 작음 — 그래서 Forbes 기준 개인 자산은 $0.3B 수준.",
    "wealthAcceleratorsKo": [
      "비누·치약(트리오·2080·케라시스) 한국 점유율",
      "화장품(에이지투웨니스·루나) 중국 K-뷰티 수출",
      "AK플라자 부동산 + 제주항공 LCC 사업"
    ],
    "structuralAdvantagesKo": [
      "한국 최초 여성 CEO 50년 단독 통솔",
      "장남 채형석 + 차남 채동석 형제 분담 운영",
      "AK홀딩스 지주체제로 가문 지분 결집"
    ],
    "currentAssetAllocationKo": "AK홀딩스 + 애경산업 + 제주항공 지분이 자산의 핵심. 그룹 규모 6조원, 본인 개인 자산은 그 중 작은 부분."
  },
  "personalTraitsKo": [
    "한국 최초 여성 CEO",
    "남편 사후 가업 인수 50년 운영",
    "여성경제인협회 초대 회장",
    "은둔형 오너",
    "88세에 대국민 사과한 책임형 회장"
  ],
  "characterKo": {
    "strengths": "남편 갑작스런 별세 후 평범한 주부에서 한국 최초 여성 CEO로의 전환. 비누 1개 회사를 41개 계열사·6조원 그룹으로 50년간 직접 키워낸 끈기. 한국 여성 기업가 1세대의 공식 정체성을 만든 협회 활동.",
    "weaknesses": "은둔형 오너 스타일 — 평소 언론 노출이 적어 대중 친밀감 부족. 2024 제주항공 참사 직전까지 사실상 일선에서 떨어져 있었던 거리감. 가족 경영의 고질적 의사결정 구조.",
    "motivation": "남편의 사업을 본인 손으로 지키고 키워야 한다는 사명감. 한국 여성 기업가의 1세대 정체성과 후대에 대한 책임.",
    "legacy": "한국 최초 여성 CEO이자 한국 여성 기업가 1세대의 표준. 다만 그 50년 끝에 제주항공 참사라는 평생 가장 큰 책임을 89세에 떠안은 인물."
  },
  "failures": [
    {
      "year": 1970,
      "description": "Husband Chae Mong-in's sudden death from a heart attack thrust her, a 34-year-old housewife with no business training, into running a soap company alone with four children to raise.",
      "descriptionKo": "남편 채몽인의 갑작스런 심장마비. 34세 평범한 주부에 4자녀를 둔 채로 비누 회사 단독 운영자가 됐습니다. 본인의 준비된 결정이 아닌 운명의 압박.",
      "lesson": "Sometimes the founder's role isn't chosen — it's inherited overnight. The ability to operate without preparation is itself a competitive moat.",
      "lessonKo": "창업자 자리가 본인 선택이 아니라 하룻밤 만에 떨어지기도 합니다. 준비 없이 운영해내는 능력 자체가 경쟁우위가 됩니다.",
      "source": "https://www.businesspost.co.kr/BP?command=print&idxno=36492"
    },
    {
      "year": 2024,
      "description": "Jeju Air Flight 2216 crashed at Muan International Airport on December 29, killing 179 of 181 onboard. AK Holdings owns 50.37% of Jeju Air. The 88-year-old chair, normally reclusive, had to issue a public apology as the group's reputation collapsed and consumer boycott followed.",
      "descriptionKo": "2024년 12월 29일 제주항공 7C2216편 무안 참사. 181명 중 179명 사망. AK홀딩스가 제주항공 50.37% 지배. 평소 은둔하던 88세 회장이 직접 대국민 공식 사과. 애경 불매운동까지 확산되며 그룹 평판이 한순간에 붕괴.",
      "lesson": "A 50-year operating record can be eclipsed by a single low-probability tail event in a side business. Diversification into safety-critical industries (aviation) raises the cost of failure across the entire group.",
      "lessonKo": "50년 운영 실적도 부속 사업 한 건의 꼬리 사건으로 가려질 수 있습니다. 안전 중심 산업(항공)으로의 다각화는 실패 비용을 그룹 전체로 확장합니다.",
      "source": "https://www.bizhankook.com/bk/article/28863"
    },
    {
      "year": 2024,
      "description": "Even before the air disaster, Aekyung's earnings had halved year-over-year, with both Aekyung Industrial and AK Plaza struggling. The group was already in 'deepening worry mode' when the crash hit.",
      "descriptionKo": "참사 이전부터 애경 실적은 흑자 1년 만에 반 토막. 애경산업·AK플라자 동시 부진. 위기가 이미 깊어지던 상황에서 참사가 덮친 구조.",
      "lesson": "When the operating cycle is already weak, an external shock has nothing to absorb the blow. Cash and resilience must be built before the storm.",
      "lessonKo": "운영 사이클이 이미 약할 때 외부 충격은 흡수될 곳이 없습니다. 현금과 회복력은 폭풍 전에 쌓아둬야 합니다.",
      "source": "https://www.sisajournal.com/news/articleView.html?idxno=329737"
    }
  ],
  "wealthHistory": [
    {"year": 2025, "netWorth": "$0.3B (약 0.4조원)", "sourceKo": "Forbes 추정 — 본인 직접 보유분 기준"}
  ],
  "quotes": [
    {
      "text": "I deeply share the grief and pain that many are experiencing, and I take this responsibility heavily.",
      "textKo": "많은 분이 겪고 계신 슬픔과 고통에 깊이 통감하며, 그 책임을 무겁게 받아들이고 있습니다.",
      "context": "December 30, 2024 public apology after Jeju Air Flight 2216 disaster",
      "contextKo": "2024년 12월 30일 제주항공 무안 참사 대국민 사과",
      "source": "https://imnews.imbc.com/news/2024/econo/article/6671885_36452.html"
    }
  ],
  "books": {
    "authored": [],
    "recommended": []
  },
  "sajuConnection": {
    "ilju": "정해",
    "geokguk": "정관격",
    "summaryKo": "장영신의 사주는 정화(작은 등불) 일간이 해수(큰 물) 위에 놓인 정해 일주입니다. 큰 물 위의 작은 등불은 어둠 속에서 멀리 가는 빛을 의미해, 평범한 주부였던 그녀가 1970년 남편 별세 후 어둠 같은 가업을 50년간 비추며 끌어가는 모습과 정확히 호응합니다. 격국이 정관격(체계·책임·전통적 권위로 자리를 만드는 형식)이라, 한국 최초 여성 CEO·여성경제인협회 초대 회장 같은 '제도화된 책임'의 길을 걸은 것이 사주의 결입니다. 월지 진토는 봄의 마지막 흙으로 큰 물을 가두는 둑 역할을 하니, 비누·화장품·항공·유통이라는 다각화된 자산을 한 그룹으로 묶어내는 그릇 역할을 그녀가 해낸 것과 닿습니다. 다만 정관격은 책임을 끝까지 떠안는 형식이라, 88세에 직면한 제주항공 참사 또한 사주가 마지막까지 묻는 책임의 시험으로 읽힙니다.",
    "interpretationKo": "정해 일주는 큰 물 위의 등불이라 작지만 멀리 비추는 빛의 결을 가집니다. 정관격은 주어진 자리·책임을 도구로 쓰는 패턴이라, 본인 선택이 아닌 운명으로 떨어진 가업을 50년 동안 책임지고 키워낸 흐름과 일치합니다.",
    "keyEvents": [
      {"year": 1970, "eventKo": "남편 별세 — 정관격이 짊어진 첫 책임"},
      {"year": 1972, "eventKo": "한국 최초 여성 CEO — 등불이 처음 점화된 시점"},
      {"year": 2024, "eventKo": "제주항공 참사 — 정관격이 마지막에 떠안은 책임"}
    ]
  },
  "sources": [
    "https://ko.wikipedia.org/wiki/%EC%9E%A5%EC%98%81%EC%8B%A0",
    "https://namu.wiki/w/%EC%9E%A5%EC%98%81%EC%8B%A0",
    "https://www.businesspost.co.kr/BP?command=print&idxno=36492",
    "https://www.fntimes.com/html/view.php?ud=202408252254069798dd55077bc2_18",
    "https://www.bizhankook.com/bk/article/28863",
    "https://www.sisajournal.com/news/articleView.html?idxno=329737",
    "https://imnews.imbc.com/news/2024/econo/article/6671885_36452.html",
    "https://www.businesspost.co.kr/BP?command=article_view&num=279334"
  ]
}
