{
  "id": "268",
  "name": "Ramzi Musallam",
  "childhood": {
    "birthPlace": "Dubai, United Arab Emirates",
    "birthPlaceKo": "두바이, 아랍에미리트",
    "familyBackground": "Born into prominent Emirati business family with trading heritage. Father was businessman in import-export.",
    "familyBackgroundKo": "무역 유산이 있는 저명한 에미라티 비즈니스 가족에서 태어났습니다. 아버지는 수출입 사업가였습니다.",
    "education": "Studied at universities in UAE and abroad; business and finance focus",
    "educationKo": "UAE 및 해외 대학에서 공부했습니다. 비즈니스 및 금융에 중점",
    "earlyLife": "Grew up during Dubai's rapid expansion and economic boom. Exposed to real estate and financial opportunities.",
    "earlyLifeKo": "두바이의 급속한 확장 및 경제 호황 중에 성장했습니다. 부동산 및 금융 기회에 노출되었습니다.",
    "source": null
  },
  "careerTimeline": [
    {
      "year": 1990,
      "event": "Started family business in real estate and property development",
      "eventKo": "부동산 및 재산 개발에서 가족 사업 시작"
    },
    {
      "year": 2000,
      "event": "Expanded into financial services and investment banking",
      "eventKo": "금융 서비스 및 투자 은행으로 확장"
    },
    {
      "year": 2010,
      "event": "Built major investment and holding company in Middle East",
      "eventKo": "중동에서 주요 투자 및 지주 회사 구축"
    },
    {
      "year": 2018,
      "event": "Diversified portfolio across real estate, finance, and hospitality",
      "eventKo": "부동산, 금융 및 환대 포트폴리오 다양화"
    }
  ],
  "failures": [
    {
      "year": 2008,
      "description": "Dubai real estate market crashed; property development projects faced severe losses",
      "descriptionKo": "두바이 부동산 시장 붕괴; 재산 개발 프로젝트가 심각한 손실에 직면했습니다",
      "lesson": "Real estate markets cyclical; geographic concentration creates risk",
      "lessonKo": "부동산 시장은 주기적입니다. 지리적 집중은 위험을 생성합니다",
      "source": null
    }
  ],
  "wealthHistory": [
    {
      "year": 2010,
      "netWorth": 4.5
    },
    {
      "year": 2015,
      "netWorth": 7.2
    },
    {
      "year": 2024,
      "netWorth": 10.8
    }
  ],
  "quotes": [
    {
      "text": "Dubai's transformation from trading post to global financial center shows the power of vision and execution",
      "textKo": "두바이의 무역항에서 글로벌 금융 중심지로의 변신은 비전과 실행의 힘을 보여줍니다",
      "context": "Middle East business forum, 2016",
      "contextKo": "중동 비즈니스 포럼, 2016년",
      "source": null
    }
  ],
  "books": {
    "authored": [],
    "recommended": [
      {
        "title": "Dubai Story",
        "author": "Rashid Al Maktoum",
        "note": "Understanding Middle East economic development",
        "noteKo": "중동 경제 개발 이해"
      }
    ]
  },
  "personalTraits": {
    "knownFor": "Major investor and entrepreneur in Middle East. Built successful real estate and financial services businesses. Known for investment strategy.",
    "knownForKo": "중동의 주요 투자자이자 기업가입니다. 성공적인 부동산 및 금융 서비스 비즈니스를 구축했습니다. 투자 전략으로 알려져 있습니다.",
    "philanthropy": "Supports education and social development initiatives in UAE",
    "philanthropyKo": "UAE의 교육 및 사회 개발 이니셔티브를 지원합니다",
    "controversies": null,
    "controversiesKo": null
  },
  "sajuConnection": null
}
