{
  "id": "325",
  "name": "Luis Carlos Sarmiento",
  "childhood": {
    "birthPlace": "Bogotá, Colombia",
    "birthPlaceKo": "콜롬비아 보고타",
    "familyBackground": "Colombian business family with commercial and financial interests. Father was businessman in Bogotá.",
    "familyBackgroundKo": "상업 및 금융 이익의 콜롬비아 비즈니스 가족. 아버지는 보고타의 사업가였음.",
    "education": "National University of Colombia, Business",
    "educationKo": "콜롬비아 국립 대학교, 비즈니스",
    "earlyLife": "Grew up in Bogotá's business community. Early exposure to finance, construction, and commercial enterprises shaped entrepreneurial focus.",
    "earlyLifeKo": "보고타의 비즈니스 커뮤니티에서 성장. 금융, 건설 및 상업 기업에 대한 조기 노출이 기업가 초점을 형성.",
    "source": "Colombian Business Archives"
  },
  "careerTimeline": [
    {
      "year": 1970,
      "event": "Started construction and real estate company",
      "eventKo": "건설 및 부동산 회사 시작"
    },
    {
      "year": 1990,
      "event": "Expanded into banking and financial services",
      "eventKo": "은행 및 금융 서비스로 확대"
    },
    {
      "year": 2000,
      "event": "Built major Colombian financial and real estate conglomerate",
      "eventKo": "주요 콜롬비아 금융 및 부동산 재벌 구축"
    },
    {
      "year": 2010,
      "event": "Diversified into infrastructure and energy sectors",
      "eventKo": "인프라 및 에너지 부문으로 다각화"
    }
  ],
  "failures": [],
  "wealthHistory": [
    {
      "year": 2005,
      "netWorth": 4.0
    },
    {
      "year": 2010,
      "netWorth": 6.0
    },
    {
      "year": 2015,
      "netWorth": 8.0
    },
    {
      "year": 2025,
      "netWorth": 9.9
    }
  ],
  "quotes": [],
  "books": {
    "authored": [],
    "recommended": []
  },
  "personalTraits": {
    "knownFor": "Colombian industrial magnate and financial leader. Built one of Colombia's largest conglomerates spanning finance, real estate, construction, and infrastructure.",
    "knownForKo": "콜롬비아 산업 거물이자 금융 지도자. 금융, 부동산, 건설 및 인프라에 걸친 콜롬비아 최대 규모 재벌 중 하나 구축.",
    "philanthropy": "Supports Colombian education, healthcare, and infrastructure development",
    "philanthropyKo": "콜롬비아 교육, 의료 및 인프라 발전 지원",
    "controversies": null,
    "controversiesKo": null
  },
  "sajuConnection": null
}